jupyter_iframe_commands/__init__.py
jupyter_iframe_commands/_version.py
jupyter_iframe_commands-0.3.0.data/data/share/jupyter/labextensions/jupyter-iframe-commands/package.json
jupyter_iframe_commands-0.3.0.data/data/share/jupyter/labextensions/jupyter-iframe-commands/schemas/jupyter-iframe-commands/package.json.orig
jupyter_iframe_commands-0.3.0.data/data/share/jupyter/labextensions/jupyter-iframe-commands/schemas/jupyter-iframe-commands/plugin.json
jupyter_iframe_commands-0.3.0.data/data/share/jupyter/labextensions/jupyter-iframe-commands/static/318.0c48b9fb3df1f6c5a214.js
jupyter_iframe_commands-0.3.0.data/data/share/jupyter/labextensions/jupyter-iframe-commands/static/318.0c48b9fb3df1f6c5a214.js.LICENSE.txt
jupyter_iframe_commands-0.3.0.data/data/share/jupyter/labextensions/jupyter-iframe-commands/static/remoteEntry.a4977091f52be18e7851.js
jupyter_iframe_commands-0.3.0.data/data/share/jupyter/labextensions/jupyter-iframe-commands/static/style.js
jupyter_iframe_commands-0.3.0.data/data/share/jupyter/labextensions/jupyter-iframe-commands/static/third-party-licenses.json
jupyter_iframe_commands-0.3.0.data/data/share/jupyter/labextensions/jupyter-iframe-commands/install.json
jupyter_iframe_commands-0.3.0.dist-info/METADATA
jupyter_iframe_commands-0.3.0.dist-info/WHEEL
jupyter_iframe_commands-0.3.0.dist-info/licenses/LICENSE
jupyter_iframe_commands-0.3.0.dist-info/RECORD
