Metadata-Version: 2.4
Name: jupyter_iframe_commands
Version: 0.3.0
Summary: A JupyterLab extension to facilitate integration with a host page via an IFrame
Project-URL: Homepage, https://github.com/TileDB-Inc/jupyter-iframe-commands
Project-URL: Bug Tracker, https://github.com/TileDB-Inc/jupyter-iframe-commands/issues
Author: QuantStack
License: MIT License
License-File: LICENSE
Keywords: jupyter,jupyterlab,jupyterlab-extension
Classifier: Framework :: Jupyter
Classifier: Framework :: Jupyter :: JupyterLab
Classifier: Framework :: Jupyter :: JupyterLab :: 4
Classifier: Framework :: Jupyter :: JupyterLab :: Extensions
Classifier: Framework :: Jupyter :: JupyterLab :: Extensions :: Prebuilt
Classifier: License :: OSI Approved :: BSD License
Classifier: Programming Language :: Python
Classifier: Programming Language :: Python :: 3
Classifier: Programming Language :: Python :: 3.8
Classifier: Programming Language :: Python :: 3.9
Classifier: Programming Language :: Python :: 3.10
Classifier: Programming Language :: Python :: 3.11
Classifier: Programming Language :: Python :: 3.12
Requires-Python: >=3.8
